{"nodes": [{"id": "favicon_32_png", "label": "PadPlay Favicon 32x32", "file_type": "image", "source_file": "frontend/public/favicon-32.png", "source_location": null, "source_url": null, "captured_at": null, "author": null, "contributor": null}, {"id": "rounded_square_frame", "label": "Rounded Square Frame", "file_type": "image", "source_file": "frontend/public/favicon-32.png", "source_location": null, "source_url": null, "captured_at": null, "author": null, "contributor": null}], "edges": [{"source": "favicon_32_png", "target": "padplay_brand", "relation": "represents", "confidence": "EXTRACTED", "confidence_score": 0.95, "source_file": "frontend/public/favicon-32.png", "source_location": null, "weight": 1.0}, {"source": "favicon_32_png", "target": "letter_p_monogram", "relation": "displays", "confidence": "EXTRACTED", "confidence_score": 0.95, "source_file": "frontend/public/favicon-32.png", "source_location": null, "weight": 1.0}, {"source": "favicon_32_png", "target": "teal_color_scheme", "relation": "uses", "confidence": "EXTRACTED", "confidence_score": 0.9, "source_file": "frontend/public/favicon-32.png", "source_location": null, "weight": 1.0}, {"source": "favicon_32_png", "target": "rounded_square_frame", "relation": "has_shape", "confidence": "EXTRACTED", "confidence_score": 0.9, "source_file": "frontend/public/favicon-32.png", "source_location": null, "weight": 1.0}, {"source": "letter_p_monogram", "target": "padplay_brand", "relation": "symbolizes", "confidence": "INFERRED", "confidence_score": 0.85, "source_file": "frontend/public/favicon-32.png", "source_location": null, "weight": 1.0}], "hyperedges": []}